griml/__init__.py
griml/convert/__init__.py
griml/convert/convert.py
griml/convert/raster_to_vector.py
griml/filter/__init__.py
griml/filter/filter_area.py
griml/filter/filter_margin.py
griml/filter/filter_vectors.py
griml/load/__init__.py
griml/load/load.py
griml/merge/__init__.py
griml/merge/merge_and_dissolve_all.py
griml/merge/merge_centroids.py
griml/merge/merge_vectors.py
griml/metadata/__init__.py
griml/metadata/add_metadata.py
griml/metadata/assign_certainty.py
griml/metadata/assign_id.py
griml/metadata/assign_names.py
griml/metadata/assign_regions.py
griml/metadata/assign_sources.py
griml/plot/plot_change_composite.py
griml/plot/plot_method_performance.py
griml/plot/plots_region_count.py
griml/plot/plots_region_methods.py
griml/plot/plots_region_overview.py
griml/plot/plots_region_sources.py
griml/stats/__init__.py
griml/stats/estimate_abundancy_error.py
griml/stats/estimate_area_error.py
griml/stats/inventory_general_stats.py
griml/stats/lake_area_change.py
griml/stats/method_stats.py
griml/stats/reformat.py
griml/stats/region_stats.py
griml/stats/region_stats_with_basin_info.py
griml/stats/series_general_stats.py
griml/test/__init__.py
griml/test/test.py
griml-1.0.6.dist-info/licenses/LICENSE
griml-1.0.6.dist-info/METADATA
griml-1.0.6.dist-info/WHEEL
griml-1.0.6.dist-info/top_level.txt
griml-1.0.6.dist-info/RECORD
