Metadata-Version: 2.4
Name: griml
Version: 1.0.6
Summary: A workflow for classifying ice-marginal lakes from satellite imagery and compiling lake inventories
Author-email: Penelope How <pho@geus.dk>
Maintainer-email: Penelope How <pho@geus.dk>
License: MIT
Project-URL: Homepage, https://github.com/GEUS-Glaciology-and-Climate/GrIML
Project-URL: Bug Tracker, https://github.com/GEUS-Glaciology-and-Climate/GrIML/issues
Keywords: glaciology,remote sensing,cryosphere,ice marginal lake,ESA
Classifier: Programming Language :: Python :: 3.10
Classifier: Programming Language :: Python :: 3.11
Classifier: Programming Language :: Python :: 3.12
Classifier: Programming Language :: Python :: 3.13
Classifier: License :: OSI Approved :: MIT License
Classifier: Development Status :: 5 - Production/Stable
Classifier: Intended Audience :: Science/Research
Classifier: Natural Language :: English
Classifier: Topic :: Scientific/Engineering
Classifier: Operating System :: OS Independent
Requires-Python: >=3.10
License-File: LICENSE
Requires-Dist: geopandas
Requires-Dist: pandas
Requires-Dist: scipy
Requires-Dist: Shapely
Requires-Dist: rasterio
Dynamic: license-file
